arcade_cli/__init__.py
arcade_cli/authn.py
arcade_cli/config.py
arcade_cli/constants.py
arcade_cli/deployment.py
arcade_cli/display.py
arcade_cli/main.py
arcade_cli/new.py
arcade_cli/serve.py
arcade_cli/show.py
arcade_cli/utils.py
arcade_cli/worker.py
arcade_cli/templates/{{ toolkit_name }}/.pre-commit-config.yaml
arcade_cli/templates/{{ toolkit_name }}/.ruff.toml
arcade_cli/templates/{{ toolkit_name }}/LICENSE
arcade_cli/templates/{{ toolkit_name }}/Makefile
arcade_cli/templates/{{ toolkit_name }}/README.md
arcade_cli/templates/{{ toolkit_name }}/pyproject.toml
arcade_cli/templates/{{ toolkit_name }}/evals/eval_{{ toolkit_name }}.py
arcade_cli/templates/{{ toolkit_name }}/tests/__init__.py
arcade_cli/templates/{{ toolkit_name }}/tests/test_{{ toolkit_name }}.py
arcade_cli/templates/{{ toolkit_name }}/{{ package_name }}/__init__.py
arcade_cli/templates/{{ toolkit_name }}/{{ package_name }}/tools/__init__.py
arcade_cli/templates/{{ toolkit_name }}/{{ package_name }}/tools/hello.py
arcade_cli/toolkit_docs/__init__.py
arcade_cli/toolkit_docs/docs_builder.py
arcade_cli/toolkit_docs/templates.py
arcade_cli/toolkit_docs/utils.py
arcade_evals/__init__.py
arcade_evals/critic.py
arcade_evals/errors.py
arcade_evals/eval.py
arcade_evals/py.typed
arcade_ai-2.2.3.dist-info/METADATA
arcade_ai-2.2.3.dist-info/WHEEL
arcade_ai-2.2.3.dist-info/entry_points.txt
arcade_ai-2.2.3.dist-info/licenses/LICENSE
arcade_ai-2.2.3.dist-info/RECORD
